smartools/__init__.py
smartools/smartools.py
smartools/models/__init__.py
smartools/models/cell.py
smartools/models/cell_format.py
smartools/models/column.py
smartools/models/content.py
smartools/models/report.py
smartools/models/report_row.py
smartools/models/row.py
smartools/models/sheet.py
smartools/models/sheet_form.py
smartools/models/summary_field.py
smartools/models/enums/__init__.py
smartools/models/enums/access_level.py
smartools/models/enums/format.py
smartools/operations/__init__.py
smartools/operations/folders.py
smartools/operations/home.py
smartools/operations/reports.py
smartools/operations/sheets.py
smartools/operations/workspaces.py
smartools/types/__init__.py
smartools/types/bulk_result.py
smartools/types/cell_list.py
smartools/types/column_list.py
smartools/types/container_list.py
smartools/types/enumerated_value.py
smartools/types/form_list.py
smartools/types/row_list.py
smartools/types/typed_list.py
smartools-1.4.0.dist-info/licenses/LICENSE.txt
smartools-1.4.0.dist-info/METADATA
smartools-1.4.0.dist-info/WHEEL
smartools-1.4.0.dist-info/top_level.txt
smartools-1.4.0.dist-info/RECORD
