Metadata-Version: 2.4
Name: smartools
Version: 1.4.0
Summary: A wrapper for the smartsheet-python-sdk that monkey-patches in new methods & functionality.
Home-page: https://github.com/davocarli
Author: David Carli-Arnold
Author-email: davocarli@gmail.com
License: MIT
Keywords: Smartsheet,smartsheet-python-sdk,monkey-patch
Classifier: Development Status :: 5 - Production/Stable
Classifier: Intended Audience :: Developers
Classifier: Topic :: Software Development :: Build Tools
Classifier: License :: OSI Approved :: MIT License
Classifier: Programming Language :: Python :: 3
License-File: LICENSE.txt
Requires-Dist: smartsheet-python-sdk
Dynamic: author
Dynamic: author-email
Dynamic: classifier
Dynamic: description
Dynamic: description-content-type
Dynamic: home-page
Dynamic: keywords
Dynamic: license
Dynamic: license-file
Dynamic: requires-dist
Dynamic: summary
